json_schema_mapper/__init__.py
json_schema_mapper/json_schema_mapper.py
json_schema_mapper/mapper_types/__init__.py
json_schema_mapper/mapper_types/mapped_type.py
json_schema_mapper/mapper_types/mapping_properties.py
json_schema_mapper/type_mapper/__init__.py
json_schema_mapper/type_mapper/array_mapper.py
json_schema_mapper/type_mapper/base_type_mapper.py
json_schema_mapper/type_mapper/bool_type_mapper.py
json_schema_mapper/type_mapper/dict_close_mapper.py
json_schema_mapper/type_mapper/dict_open_mapper.py
json_schema_mapper/type_mapper/float_mapper.py
json_schema_mapper/type_mapper/integer_type_mapper.py
json_schema_mapper/type_mapper/interface_type_mapper.py
json_schema_mapper/type_mapper/optional_mapper.py
json_schema_mapper/type_mapper/semi_colon_mapper.py
json_schema_mapper/type_mapper/string_mapper.py
json_schema_mapper/utils/__init__.py
json_schema_mapper-0.0.2.dist-info/METADATA
json_schema_mapper-0.0.2.dist-info/WHEEL
json_schema_mapper-0.0.2.dist-info/top_level.txt
json_schema_mapper-0.0.2.dist-info/RECORD
